{
  "editorVersion": "6.4.7",
  "docType": "5",
  "title": "Wiring Diagram",
  "description": "",
  "colors": {},
  "schematics": [
    {
      "docType": "1",
      "title": "Sheet_1",
      "description": "",
      "dataStr": {
        "head": {
          "docType": "1",
          "editorVersion": "6.4.7",
          "newgId": true,
          "c_para": {
            "Prefix Start": "1"
          },
          "c_spiceCmd": null
        },
        "canvas": "CA~1000~1000~#FFFFFF~yes~#CCCCCC~5~1000~1000~line~5~pixel~5~0~0",
        "shape": [
          "LIB~0~-806~package`NONE`BOM_Manufacturer Part`?`spicePre`.`~~0~frame_lib_1~~~0~~yes~yes#@$T~N~571.359375~-809~0~#000080~Arial~~~~~comment~A~0~start~gge77~0~#@$PT~M 206 -796 L 206 -806 M 206 -10 L 206 0 M 402 -796 L 402 -806 M 402 -10 L 402 0 M 598 -796 L 598 -806 M 598 -10 L 598 0 M 794 -796 L 794 -806 M 794 -10 L 794 0 M 990 -796 L 990 -806 M 990 -10 L 990 0 M 10 -600 L 0 -600 M 1139 -600 L 1149 -600 M 10 -404 L 0 -404 M 1139 -404 L 1149 -404 M 10 -208 L 0 -208 M 1139 -208 L 1149 -208 M 10 -12 L 0 -12 M 1139 -12 L 1149 -12~#880000~1~0~none~gge6~0~frame_tick#@$T~P~571.3828125~-818~0~#000080~Arial~~~~~comment~A~0~start~gge76~0~#@$T~L~1.5~-698~0~#880000~~~~~~comment~A~1~start~gge7~0~frame_tick#@$T~L~1140.5~-698~0~#880000~~~~~~comment~A~1~start~gge9~0~frame_tick#@$T~L~1.5~-502~0~#880000~~~~~~comment~B~1~start~gge11~0~frame_tick#@$T~L~1140.5~-502~0~#880000~~~~~~comment~B~1~start~gge13~0~frame_tick#@$T~L~1.5~-306~0~#880000~~~~~~comment~C~1~start~gge15~0~frame_tick#@$T~L~1140.5~-306~0~#880000~~~~~~comment~C~1~start~gge17~0~frame_tick#@$T~L~1.5~-110~0~#880000~~~~~~comment~D~1~start~gge19~0~frame_tick#@$T~L~1140.5~-110~0~#880000~~~~~~comment~D~1~start~gge21~0~frame_tick#@$T~L~108~-797.5~0~#880000~~~~~~comment~1~1~start~gge23~0~frame_tick#@$T~L~108~-1.5~0~#880000~~~~~~comment~1~1~start~gge25~0~frame_tick#@$T~L~304~-797.5~0~#880000~~~~~~comment~2~1~start~gge27~0~frame_tick#@$T~L~304~-1.5~0~#880000~~~~~~comment~2~1~start~gge29~0~frame_tick#@$T~L~500~-797.5~0~#880000~~~~~~comment~3~1~start~gge31~0~frame_tick#@$T~L~500~-1.5~0~#880000~~~~~~comment~3~1~start~gge33~0~frame_tick#@$T~L~696~-797.5~0~#880000~~~~~~comment~4~1~start~gge35~0~frame_tick#@$T~L~696~-1.5~0~#880000~~~~~~comment~4~1~start~gge37~0~frame_tick#@$T~L~892~-797.5~0~#880000~~~~~~comment~5~1~start~gge39~0~frame_tick#@$T~L~892~-1.5~0~#880000~~~~~~comment~5~1~start~gge?~0~frame_tick#@$R~10~-796~~~1129~786~#880000~1~0~none~gge42~0~frame_innerbox#@$R~0~-806~~~1149~806~#880000~1~0~none~gge43~0~frame_outbox#@$R~694.99995~-90~~~444~80~#880000~1~0~none~gge44~0~frame_hitarea#@$PL~695.1 -50.75 1138.63 -50.75~#880000~1~0~none~gge45~0#@$PL~799.63 -30.75 1138.63 -30.75~#880000~1~0~none~gge46~0#@$PL~1059.61 -89.93 1059.63 -50.75~#880000~1~0~none~gge47~0#@$PL~1059.63 -50.75 1059.63 -30.75~#880000~1~0~none~gge48~0#@$T~L~699.99995~-77~0~#880000~~8pt~~~~comment~TITLE:~1~start~gge49~0~pinpart#@$T~L~757.62495~-64.41~0~#0000FF~~10pt~~~~comment~Complete Device Wiring Schematic~1~start~gge51~0~frame_title#@$T~L~1064.62495~-63.75~0~#880000~~8pt~~~~comment~REV:~1~start~gge53~0~pinpart#@$T~L~1102.62495~-63.75~0~#0000FF~~9pt~~~~comment~1.0~1~start~gge55~0~frame_version#@$T~L~804.62495~-15~0~#880000~~8pt~~~~comment~Date:~1~start~gge57~0~pinpart#@$T~L~851.62495~-14.52~0~#0000FF~~9pt~~~~comment~2020-10-04~1~start~gge59~0~frame_date#@$T~L~1063.62495~-35~0~#880000~~8pt~~~~comment~Sheet:~1~start~gge61~0~pinpart#@$T~L~1108.62495~-34.52~0~#0000FF~~9pt~~~~comment~1/1~1~start~gge63~0~frame_sheet#@$T~L~943.62495~-14.75~0~#880000~~8pt~~~~comment~Drawn By:~1~start~gge65~0~pinpart#@$T~L~1008.63~-14.75~0~#0000FF~~9pt~~~~comment~mporeilly~1~start~gge67~0~frame_drawn#@$T~L~804.62495~-36.75~0~#880000~~8pt~~~~comment~Company:~1~start~gge69~0~pinpart#@$T~L~871.24995~-36.64~0~#0000FF~~9pt~~~~comment~University of Calgary~1~start~gge71~0~frame_company#@$PL~799.63 -50.75 799.63 -10.75~#880000~1~0~none~gge73~0",
          "LIB~535~-695~package`POLOLU-DRV8825`Contributor`sagedot`spicePre`G`spiceSymbolName`POLOLU-DRV8825`BOM_Manufacturer Part``~~0~gge550340d1e12be91d~62c0131eccee4ac2b7e66f4da792933e~55a898e5736145b183902fc560223d12~0~~yes~yes#@$T~N~529.3671875~-706.5625~0~#000080~Arial~~~~~comment~POLOLU-DRV8825~1~start~gge4740~0~#@$T~P~561.1796875~-717~0~#000080~Arial~~~~~comment~G$1~0~start~gge6877~0~#@$P~show~3~EN_N~515~-695~180~gge4744~0^^515~-695^^M 515 -695 h 19.685~#A54B4B^^1~544.84~-692.047~0~EN_N~start~~4.5pt~#A54B4B^^1~523.19~-696.97~0~EN_N~end~~4.5pt~#A54B4B^^0~531~-695^^0~M 534 -692 L 537 -695 L 534 -698#@$P~show~3~M0~515~-685~180~gge4751~0^^515~-685^^M 515 -685 h 19.685~#A54B4B^^1~544.84~-682.047~0~M0~start~~4.5pt~#A54B4B^^1~523.19~-686.969~0~M0~end~~4.5pt~#A54B4B^^0~531~-685^^0~M 534 -682 L 537 -685 L 534 -688#@$P~show~3~M1~515~-675~180~gge4758~0^^515~-675^^M 515 -675 h 19.685~#A54B4B^^1~544.84~-672.047~0~M1~start~~4.5pt~#A54B4B^^1~523.19~-676.969~0~M1~end~~4.5pt~#A54B4B^^0~531~-675^^0~M 534 -672 L 537 -675 L 534 -678#@$P~show~3~M2~515~-665~180~gge4765~0^^515~-665^^M 515 -665 h 19.685~#A54B4B^^1~544.84~-662.047~0~M2~start~~4.5pt~#A54B4B^^1~523.19~-666.969~0~M2~end~~4.5pt~#A54B4B^^0~531~-665^^0~M 534 -662 L 537 -665 L 534 -668#@$P~show~3~RST_N~515~-655~180~gge4772~0^^515~-655^^M 515 -655 h 19.685~#A54B4B^^1~544.84~-652.047~0~RST_N~start~~4.5pt~#A54B4B^^1~523.19~-656.969~0~RST_N~end~~4.5pt~#A54B4B^^0~531~-655^^0~M 534 -652 L 537 -655 L 534 -658#@$P~show~3~SLP_N~515~-645~180~gge4779~0^^515~-645^^M 515 -645 h 19.685~#A54B4B^^1~544.84~-642.047~0~SLP_N~start~~4.5pt~#A54B4B^^1~523.19~-646.969~0~SLP_N~end~~4.5pt~#A54B4B^^0~531~-645^^0~M 534 -642 L 537 -645 L 534 -648#@$P~show~3~STEP_N~515~-635~180~gge4786~0^^515~-635^^M 515 -635 h 19.685~#A54B4B^^1~544.84~-632.047~0~STEP~start~~4.5pt~#A54B4B^^1~523.19~-636.969~0~STEP_N~end~~4.5pt~#A54B4B^^0~531~-635^^0~M 534 -632 L 537 -635 L 534 -638#@$P~show~3~DIR~515~-625~180~gge4793~0^^515~-625^^M 515 -625 h 19.685~#A54B4B^^1~544.84~-622.047~0~DIR~start~~4.5pt~#A54B4B^^1~523.19~-626.969~0~DIR~end~~4.5pt~#A54B4B^^0~531~-625^^0~M 534 -622 L 537 -625 L 534 -628#@$P~show~3~GND~625~-625~0~gge4800~0^^625~-625^^M 625 -625 h -19.685~#A54B4B^^1~595.79~-622.047~0~GND~end~~4.5pt~#A54B4B^^1~617.44~-626.969~0~GND~start~~4.5pt~#A54B4B^^0~609~-625^^0~M 606 -628 L 603 -625 L 606 -622#@$P~show~3~FLT_N~625~-635~0~gge4807~0^^625~-635^^M 625 -635 h -19.685~#A54B4B^^1~595.79~-632.047~0~FLT_N~end~~4.5pt~#A54B4B^^1~617.44~-636.969~0~FLT_N~start~~4.5pt~#A54B4B^^0~609~-635^^0~M 606 -638 L 603 -635 L 606 -632#@$P~show~3~A2~625~-645~0~gge4814~0^^625~-645^^M 625 -645 h -19.685~#A54B4B^^1~595.79~-642.047~0~A2~end~~4.5pt~#A54B4B^^1~617.44~-646.969~0~A2~start~~4.5pt~#A54B4B^^0~609~-645^^0~M 606 -648 L 603 -645 L 606 -642#@$P~show~3~A1~625~-655~0~gge4821~0^^625~-655^^M 625 -655 h -19.685~#A54B4B^^1~595.79~-652.047~0~A1~end~~4.5pt~#A54B4B^^1~617.44~-656.969~0~A1~start~~4.5pt~#A54B4B^^0~609~-655^^0~M 606 -658 L 603 -655 L 606 -652#@$P~show~3~B1~625~-665~0~gge4828~0^^625~-665^^M 625 -665 h -19.685~#A54B4B^^1~595.79~-662.047~0~B1~end~~4.5pt~#A54B4B^^1~617.44~-666.969~0~B1~start~~4.5pt~#A54B4B^^0~609~-665^^0~M 606 -668 L 603 -665 L 606 -662#@$P~show~3~B2~625~-675~0~gge4835~0^^625~-675^^M 625 -675 h -19.685~#A54B4B^^1~595.79~-672.047~0~B2~end~~4.5pt~#A54B4B^^1~617.44~-676.969~0~B2~start~~4.5pt~#A54B4B^^0~609~-675^^0~M 606 -678 L 603 -675 L 606 -672#@$P~show~3~GND2~625~-685~0~gge4842~0^^625~-685^^M 625 -685 h -19.685~#A54B4B^^1~595.79~-682.047~0~GND2~end~~4.5pt~#A54B4B^^1~617.44~-686.969~0~GND2~start~~4.5pt~#A54B4B^^0~609~-685^^0~M 606 -688 L 603 -685 L 606 -682#@$P~show~3~VMOT~625~-695~0~gge4849~0^^625~-695^^M 625 -695 h -19.685~#A54B4B^^1~595.79~-692.047~0~VMOT~end~~4.5pt~#A54B4B^^1~617.44~-696.97~0~VMOT~start~~4.5pt~#A54B4B^^0~609~-695^^0~M 606 -698 L 603 -695 L 606 -692#@$PL~535.32 -705 535.32 -615~#A54B4B~1~0~none~gge4856~0#@$PL~535.32 -615 605.32 -615~#A54B4B~1~0~none~gge4857~0#@$PL~605.32 -615 605.32 -705~#A54B4B~1~0~none~gge4858~0#@$PL~605.32 -705 535.32 -705~#A54B4B~1~0~none~gge4859~0#@$T~L~525.00875~-606~0~#A54B4B~~5.4pt~0.56~~text-after-edge~comment~Scanner Motor Controller~1~start~gge4860~0~pinpart",
          "LIB~535~-485~package`POLOLU-DRV8825`Contributor`sagedot`spicePre`G`spiceSymbolName`POLOLU-DRV8825`BOM_Manufacturer Part``~~0~ggee9d3d91fb3990462~62c0131eccee4ac2b7e66f4da792933e~55a898e5736145b183902fc560223d12~0~~yes~yes#@$T~N~529.3671875~-496.5625~0~#000080~Arial~~~~~comment~POLOLU-DRV8825~1~start~gge4864~0~#@$T~P~561.1796875~-507~0~#000080~Arial~~~~~comment~G$2~0~start~gge6876~0~#@$P~show~3~EN_N~515~-485~180~gge4868~0^^515~-485^^M 515 -485 h 19.685~#A54B4B^^1~544.84~-482.047~0~EN_N~start~~4.5pt~#A54B4B^^1~523.19~-486.97~0~EN_N~end~~4.5pt~#A54B4B^^0~531~-485^^0~M 534 -482 L 537 -485 L 534 -488#@$P~show~3~M0~515~-475~180~gge4875~0^^515~-475^^M 515 -475 h 19.685~#A54B4B^^1~544.84~-472.047~0~M0~start~~4.5pt~#A54B4B^^1~523.19~-476.97~0~M0~end~~4.5pt~#A54B4B^^0~531~-475^^0~M 534 -472 L 537 -475 L 534 -478#@$P~show~3~M1~515~-465~180~gge4882~0^^515~-465^^M 515 -465 h 19.685~#A54B4B^^1~544.84~-462.047~0~M1~start~~4.5pt~#A54B4B^^1~523.19~-466.97~0~M1~end~~4.5pt~#A54B4B^^0~531~-465^^0~M 534 -462 L 537 -465 L 534 -468#@$P~show~3~M2~515~-455~180~gge4889~0^^515~-455^^M 515 -455 h 19.685~#A54B4B^^1~544.84~-452.047~0~M2~start~~4.5pt~#A54B4B^^1~523.19~-456.97~0~M2~end~~4.5pt~#A54B4B^^0~531~-455^^0~M 534 -452 L 537 -455 L 534 -458#@$P~show~3~RST_N~515~-445~180~gge4896~0^^515~-445^^M 515 -445 h 19.685~#A54B4B^^1~544.84~-442.047~0~RST_N~start~~4.5pt~#A54B4B^^1~523.19~-446.97~0~RST_N~end~~4.5pt~#A54B4B^^0~531~-445^^0~M 534 -442 L 537 -445 L 534 -448#@$P~show~3~SLP_N~515~-435~180~gge4903~0^^515~-435^^M 515 -435 h 19.685~#A54B4B^^1~544.84~-432.047~0~SLP_N~start~~4.5pt~#A54B4B^^1~523.19~-436.97~0~SLP_N~end~~4.5pt~#A54B4B^^0~531~-435^^0~M 534 -432 L 537 -435 L 534 -438#@$P~show~3~STEP_N~515~-425~180~gge4910~0^^515~-425^^M 515 -425 h 19.685~#A54B4B^^1~544.84~-422.047~0~STEP~start~~4.5pt~#A54B4B^^1~523.19~-426.97~0~STEP_N~end~~4.5pt~#A54B4B^^0~531~-425^^0~M 534 -422 L 537 -425 L 534 -428#@$P~show~3~DIR~515~-415~180~gge4917~0^^515~-415^^M 515 -415 h 19.685~#A54B4B^^1~544.84~-412.047~0~DIR~start~~4.5pt~#A54B4B^^1~523.19~-416.97~0~DIR~end~~4.5pt~#A54B4B^^0~531~-415^^0~M 534 -412 L 537 -415 L 534 -418#@$P~show~3~GND~625~-415~0~gge4924~0^^625~-415^^M 625 -415 h -19.685~#A54B4B^^1~595.79~-412.047~0~GND~end~~4.5pt~#A54B4B^^1~617.44~-416.97~0~GND~start~~4.5pt~#A54B4B^^0~609~-415^^0~M 606 -418 L 603 -415 L 606 -412#@$P~show~3~FLT_N~625~-425~0~gge4931~0^^625~-425^^M 625 -425 h -19.685~#A54B4B^^1~595.79~-422.047~0~FLT_N~end~~4.5pt~#A54B4B^^1~617.44~-426.97~0~FLT_N~start~~4.5pt~#A54B4B^^0~609~-425^^0~M 606 -428 L 603 -425 L 606 -422#@$P~show~3~A2~625~-435~0~gge4938~0^^625~-435^^M 625 -435 h -19.685~#A54B4B^^1~595.79~-432.047~0~A2~end~~4.5pt~#A54B4B^^1~617.44~-436.97~0~A2~start~~4.5pt~#A54B4B^^0~609~-435^^0~M 606 -438 L 603 -435 L 606 -432#@$P~show~3~A1~625~-445~0~gge4945~0^^625~-445^^M 625 -445 h -19.685~#A54B4B^^1~595.79~-442.047~0~A1~end~~4.5pt~#A54B4B^^1~617.44~-446.97~0~A1~start~~4.5pt~#A54B4B^^0~609~-445^^0~M 606 -448 L 603 -445 L 606 -442#@$P~show~3~B1~625~-455~0~gge4952~0^^625~-455^^M 625 -455 h -19.685~#A54B4B^^1~595.79~-452.047~0~B1~end~~4.5pt~#A54B4B^^1~617.44~-456.97~0~B1~start~~4.5pt~#A54B4B^^0~609~-455^^0~M 606 -458 L 603 -455 L 606 -452#@$P~show~3~B2~625~-465~0~gge4959~0^^625~-465^^M 625 -465 h -19.685~#A54B4B^^1~595.79~-462.047~0~B2~end~~4.5pt~#A54B4B^^1~617.44~-466.97~0~B2~start~~4.5pt~#A54B4B^^0~609~-465^^0~M 606 -468 L 603 -465 L 606 -462#@$P~show~3~GND2~625~-475~0~gge4966~0^^625~-475^^M 625 -475 h -19.685~#A54B4B^^1~595.79~-472.047~0~GND2~end~~4.5pt~#A54B4B^^1~617.44~-476.97~0~GND2~start~~4.5pt~#A54B4B^^0~609~-475^^0~M 606 -478 L 603 -475 L 606 -472#@$P~show~3~VMOT~625~-485~0~gge4973~0^^625~-485^^M 625 -485 h -19.685~#A54B4B^^1~595.79~-482.047~0~VMOT~end~~4.5pt~#A54B4B^^1~617.44~-486.97~0~VMOT~start~~4.5pt~#A54B4B^^0~609~-485^^0~M 606 -488 L 603 -485 L 606 -482#@$PL~535.32 -495 535.32 -405~#A54B4B~1~0~none~gge4980~0#@$PL~535.32 -405 605.32 -405~#A54B4B~1~0~none~gge4981~0#@$PL~605.32 -405 605.32 -495~#A54B4B~1~0~none~gge4982~0#@$PL~605.32 -495 535.32 -495~#A54B4B~1~0~none~gge4983~0#@$T~L~515.00875~-396~0~#A54B4B~~5.4pt~0.56~~text-after-edge~comment~Drive Wheels Motor Controller~1~start~gge4984~0~pinpart",
          "LIB~280~-575~package`HDR-20X2/2.54`Contributor`Sases`BOM_Supplier`Adafruit`Manufacturer`Raspberry Pi`BOM_Supplier Part`3775`BOM_Manufacturer Part`Raspberry Pi 3 - Model B+ - 1.4GHz Cortex-A53 with 1GB RAM`spicePre`R`spiceSymbolName`Raspberry Pi 3 B+`~~0~ggeadb3684eb0bcfa88~3d37db685f1ddbdfe7db6c1cd26cca5a~e9eed5e5b53942f88f2b9f7b774091af~0~~yes~yes#@$T~N~227.0234375~-676.9453125~0~#000080~Arial~~~~~comment~Raspberry Pi 3 B+~1~start~gge6303~0~#@$T~P~249.625~-687.234375~0~#000080~Arial~~~~~comment~RPI1~0~start~gge6875~0~#@$R~210~-675~~~100~210~#000000~1~0~none~gge6307~0~#@$P~show~4~1~190~-665~0~gge6308~0^^190~-665^^M 190 -665 h 20~#FF0000^^1~212~-662~0~3.3V~start~~~#FF0000^^1~205~-666~0~1~end~~~#FF0000^^0~213~-665^^0~M 210 -668 L 207 -665 L 210 -662#@$P~show~4~2~330~-665~180~gge6315~0^^330~-665^^M 330 -665 h -20~#FF0000^^1~308~-662~0~5V~end~~~#FF0000^^1~315~-666~0~2~start~~~#FF0000^^0~307~-665^^0~M 310 -662 L 313 -665 L 310 -668#@$P~show~3~3~190~-655~0~gge6322~0^^190~-655^^M 190 -655 h 20~#0066CC^^1~212~-652~0~GPIO2/SDA~start~~~#0066CC^^1~205~-656~0~3~end~~~#0066CC^^0~213~-655^^0~M 210 -658 L 207 -655 L 210 -652#@$P~show~4~4~330~-655~180~gge6329~0^^330~-655^^M 330 -655 h -20~#FF0000^^1~308~-652~0~5V~end~~~#FF0000^^1~315~-656~0~4~start~~~#FF0000^^0~307~-655^^0~M 310 -652 L 313 -655 L 310 -658#@$P~show~3~5~190~-645~0~gge6336~0^^190~-645^^M 190 -645 h 20~#0066CC^^1~212~-642~0~GPIO3/SCL~start~~~#0066CC^^1~205~-646~0~5~end~~~#0066CC^^0~213~-645^^0~M 210 -648 L 207 -645 L 210 -642#@$P~show~0~6~330~-645~180~gge6343~0^^330~-645^^M 330 -645 h -20~#333333^^1~308~-642~0~GND~end~~~#333333^^1~315~-646~0~6~start~~~#333333^^0~307~-645^^0~M 310 -642 L 313 -645 L 310 -648#@$P~show~3~7~190~-635~0~gge6350~0^^190~-635^^M 190 -635 h 20~#006600^^1~212~-632~0~GPIO4~start~~~#006600^^1~205~-636~0~7~end~~~#006600^^0~213~-635^^0~M 210 -638 L 207 -635 L 210 -632#@$P~show~3~8~330~-635~180~gge6357~0^^330~-635^^M 330 -635 h -20~#0066CC^^1~308~-632~0~GPIO14~end~~~#0066CC^^1~315~-636~0~8~start~~~#0066CC^^0~307~-635^^0~M 310 -632 L 313 -635 L 310 -638#@$P~show~0~9~190~-625~0~gge6364~0^^190~-625^^M 190 -625 h 20~#000000^^1~212~-622~0~GND~start~~~#000000^^1~205~-626~0~9~end~~~#000000^^0~213~-625^^0~M 210 -628 L 207 -625 L 210 -622#@$P~show~3~10~330~-625~180~gge6371~0^^330~-625^^M 330 -625 h -20~#0066CC^^1~308~-622~0~GPIO15~end~~~#0066CC^^1~315~-626~0~10~start~~~#0066CC^^0~307~-625^^0~M 310 -622 L 313 -625 L 310 -628#@$P~show~3~11~190~-615~0~gge6378~0^^190~-615^^M 190 -615 h 20~#006600^^1~212~-612~0~GPIO17~start~~~#006600^^1~205~-616~0~11~end~~~#006600^^0~213~-615^^0~M 210 -618 L 207 -615 L 210 -612#@$P~show~3~12~330~-615~180~gge6385~0^^330~-615^^M 330 -615 h -20~#006600^^1~308~-612~0~GPIO18~end~~~#006600^^1~315~-616~0~12~start~~~#006600^^0~307~-615^^0~M 310 -612 L 313 -615 L 310 -618#@$P~show~3~13~190~-605~0~gge6392~0^^190~-605^^M 190 -605 h 20~#006600^^1~212~-602~0~GPIO27~start~~~#006600^^1~205~-606~0~13~end~~~#006600^^0~213~-605^^0~M 210 -608 L 207 -605 L 210 -602#@$P~show~0~14~330~-605~180~gge6399~0^^330~-605^^M 330 -605 h -20~#000000^^1~308~-602~0~GND~end~~~#000000^^1~315~-606~0~14~start~~~#000000^^0~307~-605^^0~M 310 -602 L 313 -605 L 310 -608#@$P~show~3~15~190~-595~0~gge6406~0^^190~-595^^M 190 -595 h 20~#006600^^1~212~-592~0~GPIO22~start~~~#006600^^1~205~-596~0~15~end~~~#006600^^0~213~-595^^0~M 210 -598 L 207 -595 L 210 -592#@$P~show~3~16~330~-595~180~gge6413~0^^330~-595^^M 330 -595 h -20~#006600^^1~308~-592~0~GPIO23~end~~~#006600^^1~315~-596~0~16~start~~~#006600^^0~307~-595^^0~M 310 -592 L 313 -595 L 310 -598#@$P~show~4~17~190~-585~0~gge6420~0^^190~-585^^M 190 -585 h 20~#FF0000^^1~212~-582~0~3.3V~start~~~#FF0000^^1~205~-586~0~17~end~~~#FF0000^^0~213~-585^^0~M 210 -588 L 207 -585 L 210 -582#@$P~show~3~18~330~-585~180~gge6427~0^^330~-585^^M 330 -585 h -20~#006600^^1~308~-582~0~GPIO24~end~~~#006600^^1~315~-586~0~18~start~~~#006600^^0~307~-585^^0~M 310 -582 L 313 -585 L 310 -588#@$P~show~3~19~190~-575~0~gge6434~0^^190~-575^^M 190 -575 h 20~#0066CC^^1~212~-572~0~GPIO10~start~~~#0066CC^^1~205~-576~0~19~end~~~#0066CC^^0~213~-575^^0~M 210 -578 L 207 -575 L 210 -572#@$P~show~0~20~330~-575~180~gge6441~0^^330~-575^^M 330 -575 h -20~#000000^^1~308~-572~0~GND~end~~~#000000^^1~315~-576~0~20~start~~~#000000^^0~307~-575^^0~M 310 -572 L 313 -575 L 310 -578#@$P~show~3~21~190~-565~0~gge6448~0^^190~-565^^M 190 -565 h 20~#0066CC^^1~212~-562~0~GPIO9~start~~~#0066CC^^1~205~-566~0~21~end~~~#0066CC^^0~213~-565^^0~M 210 -568 L 207 -565 L 210 -562#@$P~show~3~22~330~-565~180~gge6455~0^^330~-565^^M 330 -565 h -20~#006600^^1~308~-562~0~GPIO25~end~~~#006600^^1~315~-566~0~22~start~~~#006600^^0~307~-565^^0~M 310 -562 L 313 -565 L 310 -568#@$P~show~3~23~190~-555~0~gge6462~0^^190~-555^^M 190 -555 h 20~#0066CC^^1~212~-552~0~GPIO11~start~~~#0066CC^^1~205~-556~0~23~end~~~#0066CC^^0~213~-555^^0~M 210 -558 L 207 -555 L 210 -552#@$P~show~3~24~330~-555~180~gge6469~0^^330~-555^^M 330 -555 h -20~#0066CC^^1~308~-552~0~GPIO8~end~~~#0066CC^^1~315~-556~0~24~start~~~#0066CC^^0~307~-555^^0~M 310 -552 L 313 -555 L 310 -558#@$P~show~0~25~190~-545~0~gge6476~0^^190~-545^^M 190 -545 h 20~#000000^^1~212~-542~0~GND~start~~~#000000^^1~205~-546~0~25~end~~~#000000^^0~213~-545^^0~M 210 -548 L 207 -545 L 210 -542#@$P~show~3~26~330~-545~180~gge6483~0^^330~-545^^M 330 -545 h -20~#0066CC^^1~308~-542~0~GPIO7~end~~~#0066CC^^1~315~-546~0~26~start~~~#0066CC^^0~307~-545^^0~M 310 -542 L 313 -545 L 310 -548#@$P~show~0~27~190~-535~0~gge6490~0^^190~-535^^M 190 -535 h 20~#999999^^1~212~-532~0~DNC~start~~~#999999^^1~205~-536~0~27~end~~~#999999^^0~213~-535^^0~M 210 -538 L 207 -535 L 210 -532#@$P~show~0~28~330~-535~180~gge6497~0^^330~-535^^M 330 -535 h -20~#999999^^1~308~-532~0~DNC~end~~~#999999^^1~315~-536~0~28~start~~~#999999^^0~307~-535^^0~M 310 -532 L 313 -535 L 310 -538#@$P~show~3~29~190~-525~0~gge6504~0^^190~-525^^M 190 -525 h 20~#006600^^1~212~-522~0~GPIO5~start~~~#006600^^1~205~-526~0~29~end~~~#006600^^0~213~-525^^0~M 210 -528 L 207 -525 L 210 -522#@$P~show~0~30~330~-525~180~gge6511~0^^330~-525^^M 330 -525 h -20~#000000^^1~308~-522~0~GND~end~~~#000000^^1~315~-526~0~30~start~~~#000000^^0~307~-525^^0~M 310 -522 L 313 -525 L 310 -528#@$P~show~3~31~190~-515~0~gge6518~0^^190~-515^^M 190 -515 h 20~#006600^^1~212~-512~0~GPIO6~start~~~#006600^^1~205~-516~0~31~end~~~#006600^^0~213~-515^^0~M 210 -518 L 207 -515 L 210 -512#@$P~show~3~32~330~-515~180~gge6525~0^^330~-515^^M 330 -515 h -20~#006600^^1~308~-512~0~GPIO12~end~~~#006600^^1~315~-516~0~32~start~~~#006600^^0~307~-515^^0~M 310 -512 L 313 -515 L 310 -518#@$P~show~3~33~190~-505~0~gge6532~0^^190~-505^^M 190 -505 h 20~#006600^^1~212~-502~0~GPIO13~start~~~#006600^^1~205~-506~0~33~end~~~#006600^^0~213~-505^^0~M 210 -508 L 207 -505 L 210 -502#@$P~show~0~34~330~-505~180~gge6539~0^^330~-505^^M 330 -505 h -20~#000000^^1~308~-502~0~GND~end~~~#000000^^1~315~-506~0~34~start~~~#000000^^0~307~-505^^0~M 310 -502 L 313 -505 L 310 -508#@$P~show~3~35~190~-495~0~gge6546~0^^190~-495^^M 190 -495 h 20~#006600^^1~212~-492~0~GPIO19~start~~~#006600^^1~205~-496~0~35~end~~~#006600^^0~213~-495^^0~M 210 -498 L 207 -495 L 210 -492#@$P~show~3~36~330~-495~180~gge6553~0^^330~-495^^M 330 -495 h -20~#006600^^1~308~-492~0~GPIO16~end~~~#006600^^1~315~-496~0~36~start~~~#006600^^0~307~-495^^0~M 310 -492 L 313 -495 L 310 -498#@$P~show~3~37~190~-485~0~gge6560~0^^190~-485^^M 190 -485 h 20~#006600^^1~212~-482~0~GPIO26~start~~~#006600^^1~205~-486~0~37~end~~~#006600^^0~213~-485^^0~M 210 -488 L 207 -485 L 210 -482#@$P~show~3~38~330~-485~180~gge6567~0^^330~-485^^M 330 -485 h -20~#006600^^1~308~-482~0~GPIO20~end~~~#006600^^1~315~-486~0~38~start~~~#006600^^0~307~-485^^0~M 310 -482 L 313 -485 L 310 -488#@$P~show~0~39~190~-475~0~gge6574~0^^190~-475^^M 190 -475 h 20~#000000^^1~212~-472~0~GND~start~~~#000000^^1~205~-476~0~39~end~~~#000000^^0~213~-475^^0~M 210 -478 L 207 -475 L 210 -472#@$P~show~3~40~330~-475~180~gge6581~0^^330~-475^^M 330 -475 h -20~#006600^^1~308~-472~0~GPIO21~end~~~#006600^^1~315~-476~0~40~start~~~#006600^^0~307~-475^^0~M 310 -472 L 313 -475 L 310 -478",
          "W~625 -415 625 -360 190 -360 190 -475~#008800~1~0~none~gge6878~0",
          "W~330 -575 665 -575 665 -625 625 -625~#008800~1~0~none~gge6879~0",
          "F~part_netLabel_VCC~180~-245~0~gge6880~~0^^180~-245^^12 VDC 32 Wh~#000000~147.1640625~-260.9375~0~start~1~Times New Roman~9pt~gge6882^^PL~180 -255 180 -245~#000000~1~0~none~gge6884~0^^PL~175 -255 185 -255~#000000~1~0~transparent~gge6885~0",
          "T~L~150~-275~0~#0000FF~~9pt~~~~comment~Drill Battery~1~start~gge6892~0~pinpart"
        ],
        "BBox": {
          "x": 0,
          "y": -806.9,
          "width": 1149,
          "height": 807.3
        },
        "colors": {}
      }
    }
  ]
}